<annotation>
	<folder>data</folder>
	<filename>319.jpg</filename>
	<path>C:/data/new/img/319.xml</path>
	<source>
		<database>Unknown</database>
	</source>
	<size>
		<width>2973</width>
		<height>2908</height>
		<depth>3</depth>
	</size>
	<segmented>0</segmented>
	<object>
		<name>equation</name>
		<pose>Unspecified</pose>
		<truncated>0</truncated>
		<difficult>0</difficult>
		<bndbox>
			<xmin>165</xmin>
			<ymin>341</ymin>
			<xmax>827</xmax>
			<ymax>516</ymax>
		</bndbox>
	</object>
	<object>
		<name>equation</name>
		<pose>Unspecified</pose>
		<truncated>0</truncated>
		<difficult>0</difficult>
		<bndbox>
			<xmin>171</xmin>
			<ymin>579</ymin>
			<xmax>833</xmax>
			<ymax>782</ymax>
		</bndbox>
	</object>
	<object>
		<name>equation</name>
		<pose>Unspecified</pose>
		<truncated>0</truncated>
		<difficult>0</difficult>
		<bndbox>
			<xmin>168</xmin>
			<ymin>829</ymin>
			<xmax>812</xmax>
			<ymax>1016</ymax>
		</bndbox>
	</object>
	<object>
		<name>equation</name>
		<pose>Unspecified</pose>
		<truncated>0</truncated>
		<difficult>0</difficult>
		<bndbox>
			<xmin>174</xmin>
			<ymin>1088</ymin>
			<xmax>818</xmax>
			<ymax>1250</ymax>
		</bndbox>
	</object>
	<object>
		<name>equation</name>
		<pose>Unspecified</pose>
		<truncated>0</truncated>
		<difficult>0</difficult>
		<bndbox>
			<xmin>162</xmin>
			<ymin>1319</ymin>
			<xmax>830</xmax>
			<ymax>1494</ymax>
		</bndbox>
	</object>
	<object>
		<name>equation</name>
		<pose>Unspecified</pose>
		<truncated>0</truncated>
		<difficult>0</difficult>
		<bndbox>
			<xmin>146</xmin>
			<ymin>1582</ymin>
			<xmax>868</xmax>
			<ymax>1772</ymax>
		</bndbox>
	</object>
	<object>
		<name>equation</name>
		<pose>Unspecified</pose>
		<truncated>0</truncated>
		<difficult>0</difficult>
		<bndbox>
			<xmin>165</xmin>
			<ymin>1847</ymin>
			<xmax>849</xmax>
			<ymax>2010</ymax>
		</bndbox>
	</object>
	<object>
		<name>equation</name>
		<pose>Unspecified</pose>
		<truncated>0</truncated>
		<difficult>0</difficult>
		<bndbox>
			<xmin>137</xmin>
			<ymin>2082</ymin>
			<xmax>865</xmax>
			<ymax>2269</ymax>
		</bndbox>
	</object>
	<object>
		<name>equation</name>
		<pose>Unspecified</pose>
		<truncated>0</truncated>
		<difficult>0</difficult>
		<bndbox>
			<xmin>158</xmin>
			<ymin>2338</ymin>
			<xmax>865</xmax>
			<ymax>2529</ymax>
		</bndbox>
	</object>
	<object>
		<name>equation</name>
		<pose>Unspecified</pose>
		<truncated>0</truncated>
		<difficult>0</difficult>
		<bndbox>
			<xmin>165</xmin>
			<ymin>2591</ymin>
			<xmax>880</xmax>
			<ymax>2804</ymax>
		</bndbox>
	</object>
	<object>
		<name>equation</name>
		<pose>Unspecified</pose>
		<truncated>0</truncated>
		<difficult>0</difficult>
		<bndbox>
			<xmin>1121</xmin>
			<ymin>316</ymin>
			<xmax>1777</xmax>
			<ymax>507</ymax>
		</bndbox>
	</object>
	<object>
		<name>equation</name>
		<pose>Unspecified</pose>
		<truncated>0</truncated>
		<difficult>0</difficult>
		<bndbox>
			<xmin>1083</xmin>
			<ymin>572</ymin>
			<xmax>1843</xmax>
			<ymax>741</ymax>
		</bndbox>
	</object>
	<object>
		<name>equation</name>
		<pose>Unspecified</pose>
		<truncated>0</truncated>
		<difficult>0</difficult>
		<bndbox>
			<xmin>1133</xmin>
			<ymin>813</ymin>
			<xmax>1830</xmax>
			<ymax>1000</ymax>
		</bndbox>
	</object>
	<object>
		<name>equation</name>
		<pose>Unspecified</pose>
		<truncated>0</truncated>
		<difficult>0</difficult>
		<bndbox>
			<xmin>1130</xmin>
			<ymin>1082</ymin>
			<xmax>1805</xmax>
			<ymax>1238</ymax>
		</bndbox>
	</object>
	<object>
		<name>equation</name>
		<pose>Unspecified</pose>
		<truncated>0</truncated>
		<difficult>0</difficult>
		<bndbox>
			<xmin>1140</xmin>
			<ymin>1313</ymin>
			<xmax>1830</xmax>
			<ymax>1504</ymax>
		</bndbox>
	</object>
	<object>
		<name>equation</name>
		<pose>Unspecified</pose>
		<truncated>0</truncated>
		<difficult>0</difficult>
		<bndbox>
			<xmin>1137</xmin>
			<ymin>1575</ymin>
			<xmax>1824</xmax>
			<ymax>1754</ymax>
		</bndbox>
	</object>
	<object>
		<name>equation</name>
		<pose>Unspecified</pose>
		<truncated>0</truncated>
		<difficult>0</difficult>
		<bndbox>
			<xmin>1133</xmin>
			<ymin>1829</ymin>
			<xmax>1862</xmax>
			<ymax>2000</ymax>
		</bndbox>
	</object>
	<object>
		<name>equation</name>
		<pose>Unspecified</pose>
		<truncated>0</truncated>
		<difficult>0</difficult>
		<bndbox>
			<xmin>1149</xmin>
			<ymin>2066</ymin>
			<xmax>1833</xmax>
			<ymax>2266</ymax>
		</bndbox>
	</object>
	<object>
		<name>equation</name>
		<pose>Unspecified</pose>
		<truncated>0</truncated>
		<difficult>0</difficult>
		<bndbox>
			<xmin>1133</xmin>
			<ymin>2347</ymin>
			<xmax>1802</xmax>
			<ymax>2544</ymax>
		</bndbox>
	</object>
	<object>
		<name>equation</name>
		<pose>Unspecified</pose>
		<truncated>0</truncated>
		<difficult>0</difficult>
		<bndbox>
			<xmin>1143</xmin>
			<ymin>2600</ymin>
			<xmax>1852</xmax>
			<ymax>2816</ymax>
		</bndbox>
	</object>
	<object>
		<name>equation</name>
		<pose>Unspecified</pose>
		<truncated>0</truncated>
		<difficult>0</difficult>
		<bndbox>
			<xmin>2083</xmin>
			<ymin>282</ymin>
			<xmax>2799</xmax>
			<ymax>457</ymax>
		</bndbox>
	</object>
	<object>
		<name>equation</name>
		<pose>Unspecified</pose>
		<truncated>0</truncated>
		<difficult>0</difficult>
		<bndbox>
			<xmin>2077</xmin>
			<ymin>532</ymin>
			<xmax>2758</xmax>
			<ymax>732</ymax>
		</bndbox>
	</object>
	<object>
		<name>equation</name>
		<pose>Unspecified</pose>
		<truncated>0</truncated>
		<difficult>0</difficult>
		<bndbox>
			<xmin>2096</xmin>
			<ymin>785</ymin>
			<xmax>2821</xmax>
			<ymax>985</ymax>
		</bndbox>
	</object>
	<object>
		<name>equation</name>
		<pose>Unspecified</pose>
		<truncated>0</truncated>
		<difficult>0</difficult>
		<bndbox>
			<xmin>2083</xmin>
			<ymin>1050</ymin>
			<xmax>2852</xmax>
			<ymax>1241</ymax>
		</bndbox>
	</object>
	<object>
		<name>equation</name>
		<pose>Unspecified</pose>
		<truncated>0</truncated>
		<difficult>0</difficult>
		<bndbox>
			<xmin>2099</xmin>
			<ymin>1310</ymin>
			<xmax>2843</xmax>
			<ymax>1475</ymax>
		</bndbox>
	</object>
	<object>
		<name>equation</name>
		<pose>Unspecified</pose>
		<truncated>0</truncated>
		<difficult>0</difficult>
		<bndbox>
			<xmin>2124</xmin>
			<ymin>1547</ymin>
			<xmax>2862</xmax>
			<ymax>1750</ymax>
		</bndbox>
	</object>
	<object>
		<name>equation</name>
		<pose>Unspecified</pose>
		<truncated>0</truncated>
		<difficult>0</difficult>
		<bndbox>
			<xmin>2118</xmin>
			<ymin>1797</ymin>
			<xmax>2830</xmax>
			<ymax>2004</ymax>
		</bndbox>
	</object>
	<object>
		<name>equation</name>
		<pose>Unspecified</pose>
		<truncated>0</truncated>
		<difficult>0</difficult>
		<bndbox>
			<xmin>2143</xmin>
			<ymin>2072</ymin>
			<xmax>2855</xmax>
			<ymax>2272</ymax>
		</bndbox>
	</object>
	<object>
		<name>equation</name>
		<pose>Unspecified</pose>
		<truncated>0</truncated>
		<difficult>0</difficult>
		<bndbox>
			<xmin>2140</xmin>
			<ymin>2338</ymin>
			<xmax>2868</xmax>
			<ymax>2532</ymax>
		</bndbox>
	</object>
	<object>
		<name>equation</name>
		<pose>Unspecified</pose>
		<truncated>0</truncated>
		<difficult>0</difficult>
		<bndbox>
			<xmin>2149</xmin>
			<ymin>2600</ymin>
			<xmax>2849</xmax>
			<ymax>2822</ymax>
		</bndbox>
	</object>
</annotation>